NIWLittleUtils/__init__.py
NIWLittleUtils/codec.py
NIWLittleUtils/filesystem.py
NIWLittleUtils/random_tool.py
NIWLittleUtils-0.1.0.dev10.dist-info/DESCRIPTION.rst
NIWLittleUtils-0.1.0.dev10.dist-info/METADATA
NIWLittleUtils-0.1.0.dev10.dist-info/RECORD
NIWLittleUtils-0.1.0.dev10.dist-info/WHEEL
NIWLittleUtils-0.1.0.dev10.dist-info/metadata.json
NIWLittleUtils-0.1.0.dev10.dist-info/top_level.txt
