Metadata-Version: 2.0
Name: NIWLittleUtils
Version: 0.1.0.dev10
Summary: NIWLittleUtils is a tool collection.
Home-page: https://bitbucket.org/birdhackor/niwlittleutils
Author: NIWyclin (a.k.a. birdhackor)
Author-email: NIWLittleUtils@mymail.niwyclin.org
License: LGPLv3
Platform: UNKNOWN
Classifier: Intended Audience :: Developers
Classifier: Topic :: Software Development :: Build Tools
Classifier: License :: OSI Approved :: GNU Lesser General Public License v3 (LGPLv3)
Classifier: Programming Language :: Python
Classifier: Programming Language :: Python :: 3
Classifier: Programming Language :: Python :: 3.4
Classifier: Programming Language :: Python :: 3.5
Classifier: Programming Language :: Python :: 3.6
Requires-Dist: scandir; python_version < "3.5"
